setup.py
swaroopadipkg/__init__.py
swaroopadipkg/my_calculator.py
swaroopadipkg.egg-info/PKG-INFO
swaroopadipkg.egg-info/SOURCES.txt
swaroopadipkg.egg-info/dependency_links.txt
swaroopadipkg.egg-info/top_level.txt