Metadata-Version: 2.1
Name: swaroopadipkg
Version: 0.0.1
Summary: Swaroop's Test Python Module
Home-page: https://github.com/SwaroopPK/ADI-Modules
Author: Swaroop
Author-email: swarooppk96@gmail.com
Classifier: Programming Language :: Python :: 3
Classifier: Operating System :: OS Independent
